shared_models/__init__.py
shared_models/database/__init__.py
shared_models/database/config.py
shared_models/database/models/__init__.py
shared_models/database/models/message.py
shared_models/database/models/moderation_log.py
shared_models/database/models/user.py
shared_models/enums/__init__.py
shared_models/enums/message_state.py
shared_models/enums/moderation_result.py
shared_models/enums/moderator_type.py
shared_models/messaging/__init__.py
shared_models/messaging/exchanges.py
shared_models/messaging/models/__init__.py
shared_models/messaging/models/add_to_black_list.py
shared_models/messaging/models/error_response.py
shared_models/messaging/models/message.py
shared_models/messaging/models/message_input.py
shared_models/messaging/models/message_shown.py
shared_models/messaging/models/moderation_error.py
shared_models/messaging/models/moderation_result.py
shared_models/messaging/models/no_available_time.py
shared_models/messaging/queues/__init__.py
shared_models/messaging/queues/auto_moderator.py
shared_models/messaging/queues/bot.py
shared_models/messaging/queues/facade_message_moderator.py
shared_models/messaging/queues/manual_moderator.py
shared_models/messaging/queues/table_moderator.py
shared_models/messaging/queues/vision.py
shared_models/py.typed
facade_message_bot_shared_models-0.14.0.dist-info/METADATA
facade_message_bot_shared_models-0.14.0.dist-info/WHEEL
facade_message_bot_shared_models-0.14.0.dist-info/RECORD
