Metadata-Version: 2.3
Name: facade-message-bot-shared-models
Version: 0.14.0
Summary: 
Author: ycalk
Author-email: alosev752@gmail.com
Requires-Python: >=3.11,<4.0
Classifier: Programming Language :: Python :: 3
Classifier: Programming Language :: Python :: 3.11
Classifier: Programming Language :: Python :: 3.12
Classifier: Programming Language :: Python :: 3.13
Provides-Extra: database
Provides-Extra: full
Provides-Extra: messaging
Requires-Dist: aerich (>=0.9.1,<0.10.0) ; extra == "database"
Requires-Dist: aerich (>=0.9.1,<0.10.0) ; extra == "full"
Requires-Dist: faststream[rabbit] (>=0.5.48,<0.6.0) ; extra == "full"
Requires-Dist: faststream[rabbit] (>=0.5.48,<0.6.0) ; extra == "messaging"
Requires-Dist: tortoise-orm[asyncpg] (>=0.25.1,<0.26.0) ; extra == "database"
Requires-Dist: tortoise-orm[asyncpg] (>=0.25.1,<0.26.0) ; extra == "full"
